turtle_shapes/__init__.py
turtle_shapes/basic.py
n_shapes-0.1.0.dist-info/METADATA
n_shapes-0.1.0.dist-info/WHEEL
n_shapes-0.1.0.dist-info/top_level.txt
n_shapes-0.1.0.dist-info/RECORD
