Metadata-Version: 2.4
Name: n_shapes
Version: 0.1.0
Summary: Simple turtle-based shape drawing package
Author: Naitik
Classifier: Programming Language :: Python :: 3
Classifier: License :: OSI Approved :: MIT License
Requires-Python: >=3.6
Dynamic: author
Dynamic: classifier
Dynamic: requires-python
Dynamic: summary
